ContentAssistant/__init__.py
ContentAssistant/manager.py
ContentAssistant/test.py
contentassistant-0.0.1.dist-info/METADATA
contentassistant-0.0.1.dist-info/WHEEL
contentassistant-0.0.1.dist-info/top_level.txt
contentassistant-0.0.1.dist-info/RECORD
