Metadata-Version: 2.1
Name: contentassistant
Version: 0.0.1
Summary: Manipulação do assistente de conteúdo
Author: Caio Souza
Author-email: caios@take.net
Classifier: Development Status :: 4 - Beta
Classifier: License :: OSI Approved :: MIT License
Classifier: Operating System :: OS Independent
Classifier: Programming Language :: Python :: 3
Requires-Python: >=3.6
Requires-Dist: pandas
Requires-Dist: ujson
Requires-Dist: requests
Requires-Dist: uuid
